daiexperiments
