Metadata-Version: 2.1
Name: daiexperiments
Version: 0.0.12
Summary: dai experiments
Home-page: 
Author: S Ishan
Author-email: is9678@srmist.edu.in
License: MIT
Keywords: dai
Classifier: Development Status :: 5 - Production/Stable
Classifier: Intended Audience :: Education
Classifier: Operating System :: Microsoft :: Windows :: Windows 10
Classifier: License :: OSI Approved :: MIT License
Classifier: Programming Language :: Python :: 3
License-File: LICENSE.txt
